{
  "market_name": "Advanced Building Materials Market",
  "unit": "Billion",
  "cagr": 3.6,
  "value_2024": 94.5,
  "value_2033": 129.92,
  "REGIONAL_RANKING": {
    "first": "Asia Pacific",
    "second": "North America",
    "third": "Europe"
  },
  "EUROPE_COUNTRY_CLASSIFICATION": {
    "Germany": "dominant",
    "United Kingdom": "emerging",
    "France": "fastest_growing"
  },
  "SEGMENTS": {
    "Functionality": [
      "Structural",
      "Thermal",
      "Acoustic",
      "Waterproofing",
      "Fire-Resistant"
    ],
    "Material Type": [
      "Cement And Concrete",
      "Wood",
      "Metals",
      "Glass",
      "Insulation",
      "Other"
    ],
    "Application": [
      "Roofing",
      "Flooring",
      "Walls",
      "Facades",
      "Doors And Windows",
      "Other"
    ],
    "End Use": [
      "Residential",
      "Commercial",
      "Industrial"
    ]
  }
}