{
  "market_name": "Construction Market",
  "unit": "Trillion",
  "cagr": 4.4,
  "value_2024": 11.5,
  "value_2033": 16.94,
  "REGIONAL_RANKING": {
    "first": "Asia Pacific",
    "second": "North America",
    "third": "Europe"
  },
  "EUROPE_COUNTRY_CLASSIFICATION": {
    "Germany": "dominant",
    "United Kingdom": "fastest_growing",
    "France": "emerging"
  },
  "SEGMENTS": {
    "Type of Contractor": [
      "Large Contractor",
      "Small Contractor"
    ],
    "Entity": [
      "Public",
      "Private"
    ],
    "Type of Construction": [
      "Buildings Construction",
      "Heavy and Civil Engineering",
      "Specialty Trade Contractors",
      "Land Planning and Development"
    ],
    "End-Use Industry": [
      "Residential",
      "Commercial",
      "Industrial",
      "Government and Defense"
    ],
    "Category": [
      "Renovation",
      "New Construction"
    ]
  }
}