{
  "market_name": "EV Charger Market",
  "unit": "Billion",
  "cagr": 27.7,
  "value_2024": 7.5,
  "value_2033": 67.73,
  "REGIONAL_RANKING": {
    "first": "Asia Pacific",
    "second": "Europe",
    "third": "North America"
  },
  "EUROPE_COUNTRY_CLASSIFICATION": {
    "Germany": "dominant",
    "United Kingdom": "fastest_growing",
    "France": "emerging"
  },
  "SEGMENTS": {
    "Vehicle Type": [
      "Battery Electric Vehicle (BEV)",
      "Plug-in Hybrid Electric Vehicle (PHEV)",
      "Hybrid Electric Vehicle (HEV)"
    ],
    "Charging Type": [
      "On-board Chargers",
      "Off-board Chargers"
    ],
    "End User": [
      "Residential",
      "Commercial"
    ]
  }
}